nknsdk/__init__.py
nknsdk/client/__init__.py
nknsdk/config/__init__.py
nknsdk/config/config.py
nknsdk/crypto/__init__.py
nknsdk/crypto/account.py
nknsdk/crypto/encryption.py
nknsdk/crypto/hash.py
nknsdk/crypto/key.py
nknsdk/crypto/protocol.py
nknsdk/crypto/tools.py
nknsdk/error/__init__.py
nknsdk/error/wallet_error.py
nknsdk/network/__init__.py
nknsdk/network/api.py
nknsdk/pb/__init__.py
nknsdk/pb/block_pb2.py
nknsdk/pb/clientmessage_pb2.py
nknsdk/pb/node_pb2.py
nknsdk/pb/nodemessage_pb2.py
nknsdk/pb/sigchain_pb2.py
nknsdk/pb/transaction_pb2.py
nknsdk/serialize/__init__.py
nknsdk/serialize/serialize.py
nknsdk/transaction/__init__.py
nknsdk/transaction/payload.py
nknsdk/transaction/transaction.py
nknsdk/wallet/__init__.py
nknsdk/wallet/wallet.py
nkn_sdk-0.1.1.dist-info/LICENSE
nkn_sdk-0.1.1.dist-info/METADATA
nkn_sdk-0.1.1.dist-info/WHEEL
nkn_sdk-0.1.1.dist-info/top_level.txt
nkn_sdk-0.1.1.dist-info/RECORD
