Metadata-Version: 2.1
Name: nkn-sdk
Version: 0.1.1
Summary: NKN client and wallet SDK
Home-page: https://github.com/nknorg/nkn-sdk-py3
Author: heron
Author-email: peng.liu@nkn.org
License: UNKNOWN
Platform: UNKNOWN
Classifier: Programming Language :: Python :: 3
Classifier: License :: OSI Approved :: Apache Software License
Classifier: Operating System :: OS Independent
Requires-Python: >=3.3
Requires-Dist: pynacl
Requires-Dist: pycrypto
Requires-Dist: base58
Requires-Dist: requests
Requires-Dist: protobuf
